MANIFEST.in
PYPI_VERSION
Readme.md
setup.cfg
setup.py
bin/3663.py
bin/PictureFrame2020.py
bin/SK6812_white_test.py
bin/mqtt-for-pi3dpf.py
bin/pictureframe.sh
bin/rgb-leds.py
pi3dpf_ns/__init__.py
pi3dpf_ns/pi3dpf_base/PictureFrame2020config.py
pi3dpf_ns/pi3dpf_base/__init__.py
pi3dpf_ns/pi3dpf_base/pf.functions_obsolete.sh
pi3dpf_ns/pi3dpf_base/pf.py
pi3dpf_ns/pi3dpf_base/pf_elements.py
pi3dpf_ns/pi3dpf_base/pf_elements.py.sav
pi3dpf_ns/pi3dpf_base/pf_elements.py.sav2
pi3dpf_ns/pi3dpf_base/pf_mqtt.py
pi3dpf_ns/pi3dpf_base/pythainlp_util_date_obsolete.py
pi3dpf_ns/pi3dpf_base/suncalc_obsolete.py
pi3dpf_ns/pi3dpf_base/cfg/elements.config
pi3dpf_ns/pi3dpf_base/cfg/pf-opts
pi3dpf_ns/pi3dpf_base/cfg/pf.config
pi3dpf_ns/pi3dpf_base/cfg/positions.txt
pi3dpf_ns/pi3dpf_base/cfg/weather_1_city_obsolete.odp
pi3dpf_ns/pi3dpf_base/cfg/weather_2_cities_obsolete.odp
pi3dpf_ns/pi3dpf_base/cfg/weather_obsolete.odp
pi3dpf_ns/pi3dpf_base/cfg/icons/1x1-transparent.png
pi3dpf_ns/pi3dpf_base/cfg/icons/4x4-transparent.png
pi3dpf_ns/pi3dpf_base/cfg/pi3d/shaders/blend_new.fs
pi3dpf_ns/pi3dpf_base/cfg/pi3d/shaders/blend_new.vs
pi3dpf_ns/pi3dpf_base/cfg/pi3d/textures/.gitkeep
pi3dpf_ns/pi3dpf_base/pictures/pixabay_0000394235.jpg
pi3dpf_ns/pi3dpf_base/pictures/pixabay_0000584788.jpg
pi3dpf_ns_pi3dpf_base.egg-info/PKG-INFO
pi3dpf_ns_pi3dpf_base.egg-info/SOURCES.txt
pi3dpf_ns_pi3dpf_base.egg-info/dependency_links.txt
pi3dpf_ns_pi3dpf_base.egg-info/not-zip-safe
pi3dpf_ns_pi3dpf_base.egg-info/requires.txt
pi3dpf_ns_pi3dpf_base.egg-info/top_level.txt